{"cameraMode":{"drawMode":0,"name":"Shaded","section":"Shading Mode"},"sceneLighting":true,"audioPlay":false,"sceneViewState":{"showFog":true,"showMaterialUpdate":false,"showSkybox":true,"showFlares":true,"showImageEffects":true,"showParticleSystems":true},"in2DMode":false,"pivot":{"x":4.715216636657715,"y":9.400864601135254,"z":-9.285446166992188},"rotation":{"x":0.1049756333231926,"y":0.6493985652923584,"z":-0.09118717908859253,"w":0.7476534843444824},"size":8.228317260742188,"orthographic":false}